SongNameSplit/__init__.py
SongNameSplit-2.2.5.dist-info/METADATA
SongNameSplit-2.2.5.dist-info/WHEEL
SongNameSplit-2.2.5.dist-info/top_level.txt
SongNameSplit-2.2.5.dist-info/RECORD
