Metadata-Version: 2.1
Name: SongNameSplit
Version: 2.2.5
Summary: Seperate the song and artist name from a song title
Author: Archit Tandon
Author-email: archittandon26@gmail.com
Keywords: python,song,song name,artist,artist name
Requires-Dist: google
Requires-Dist: bs4
Requires-Dist: requests
Requires-Dist: beautifulsoup4
Requires-Dist: tqdm
